r2t/__init__.py
r2t/r2t.py
r2t-0.1.7.dist-info/METADATA
r2t-0.1.7.dist-info/WHEEL
r2t-0.1.7.dist-info/entry_points.txt
r2t-0.1.7.dist-info/top_level.txt
r2t-0.1.7.dist-info/RECORD
