Metadata-Version: 2.1
Name: r2t
Version: 0.1.7
Summary: A tool to combine multiple files from a directory and its subdirectories into a single output file
Classifier: Programming Language :: Python :: 3
Classifier: License :: OSI Approved :: MIT License
Classifier: Operating System :: OS Independent
Requires-Python: >=3.6
Requires-Dist: chardet
Provides-Extra: gui
Requires-Dist: tk ; extra == 'gui'
